LICENSE
README.md
setup.py
Beamng_Zoe/__init__.py
Beamng_Zoe/__main__.py
Beamng_Zoe/gitUtils.py
Beamng_Zoe/gpuInfo.py
Beamng_Zoe/serverConnection.py
Beamng_Zoe/steamUtils.py
Beamng_Zoe/svnUtils.py
Beamng_Zoe/tasks.py
Beamng_Zoe/utils.py
Beamng_Zoe/work.py
Beamng_Zoe.egg-info/PKG-INFO
Beamng_Zoe.egg-info/SOURCES.txt
Beamng_Zoe.egg-info/dependency_links.txt
Beamng_Zoe.egg-info/requires.txt
Beamng_Zoe.egg-info/top_level.txt