Metadata-Version: 2.1
Name: Beamng-Zoe
Version: 0.1.25
Summary: A python testing framework
Home-page: https://github.com/BeamNG/zoe
Author: Thomas Fischer
Author-email: tfischer@beamng.gmbh
License: MIT
Classifier: Development Status :: 2 - Pre-Alpha
Classifier: Intended Audience :: Developers
Classifier: License :: OSI Approved :: MIT License
Classifier: Topic :: Software Development :: Testing
Classifier: Operating System :: POSIX :: Linux
Classifier: Operating System :: Microsoft :: Windows
Classifier: Programming Language :: Python :: 3
License-File: LICENSE
